{
  "data": {
    "Rules and Regulations for PhD": [
      {
        "title": "Download Ph.D regulations",
        "link": "/programs/Ph.D_regulations_IIITT_final_2020.pdf"
      },
      {
        "title": "Amendments to Ph.D regulations",
        "link": "/programs/PhD_Amendment2023.pdf"
      }
    ],
    "Forms for PhD": [
      {
        "title": "Enrolment form",
        "link": "/PhD_Forms/1_Enrolment_form.doc"
      },
      {
        "title": "DC Proposal form",
        "link": "/PhD_Forms/2_DCProposal_form.docx"
      },
      {
        "title": "First DC Meeting Minutes",
        "link": "/PhD_Forms/3_DCMeeting_First_Minutes.docx"
      },
      {
        "title": "Registration form",
        "link": "/PhD_Forms/4_Registration_form.doc"
      },
      {
        "title": "Progress Review form",
        "link": "/PhD_Forms/5_Progress_Review_form.docx"
      },
      {
        "title": "Comprehensive Viva Proposal form",
        "link": "/PhD_Forms/6_Comprehensive_Viva_Proposal_form.docx"
      },
      {
        "title": "Comprehensive Examination Report form",
        "link": "/PhD_Forms/7_Compre_Exam_Report_form.docx"
      },
      {
        "title": "Synopsis Submission form",
        "link": "/PhD_Forms/8_Synopsis_Submission_Form.docx"
      },
      {
        "title": "CPO form",
        "link": "/PhD_Forms/8a_CPO_form.docx"
      },
      {
        "title": "Synopsis Meeting Minutes",
        "link": "/PhD_Forms/8b_Synopsis_Meeting_Minutes.docx"
      },
      {
        "title": "Form for list of External Examiners",
        "link": "/PhD_Forms/8c_Form_for_List_of_External_Examiners.docx"
      },
      {
        "title": "Guidelines for preparation of Synopsis",
        "link": "/PhD_Forms/8d_Guidelines_for_preparation_of_Synopsis.pdf"
      },
      {
        "title": "Certificate from the thesis supervisor",
        "link": "/PhD_Forms/8e_Certificate_from_the_thesis_supervisor.docx"
      },
      {
        "title": "Guidelines for preparation of thesis",
        "link": "/PhD_Forms/8f_Guidelines_for_preparation_of_Thesis.pdf"
      },
      {
        "title": "Thesis Submission form",
        "link": "/PhD_Forms/9_Thesis_Submission_form.docx"
      },
      {
        "title": "Thesis Submission Certificate",
        "link": "/PhD_Forms/9a_Thesis_Submission_Certificate.docx"
      },
      {
        "title": "No Dues form",
        "link": "/PhD_Forms/9b_No_Dues_form.docx"
      },
      {
        "title": "Compliance Report",
        "link": "/PhD_Forms/10_Compliance_Report.docx"
      },
      {
        "title": "Final DC Meeting Minutes",
        "link": "/PhD_Forms/10a_DC_Meeting_Final_Minutes.docx"
      },
      {
        "title": "Report of Oral Examination for PhD Thesis Defense",
        "link": "/PhD_Forms/11_Report_of_OralExam_for_PhD_Thesis_Defense.docx"
      }
    ]
  }
}
