{
  "CSE": [
    {
      "id": {
        "dept": "CSE",
        "deptID": "1"
      },
      "name": "Dr. G. Devasena",
      "designation": "Assistant Professor , Head of the Department",
      "Incharge": "Training and Placement, AISHE portal, NSP portal, Digilocker",
      "Institute": "Ph.D. (Anna University)",
      "VidhwanLink": "https://vidwan.inflibnet.ac.in/profile/194480",
      "researchArea": "Image Processing, Deep Learning and Machine  Learning, Video Processing, ",
      "emailID": "devasenag@iiitt.ac.in",
      "src": "/faculty/Devasena.jpg",
      "PersonalPage": "https://sites.google.com/view/devasenagiiitt/home"
    },
    {
      "id": {
        "dept": "CSE",
        "deptID": "2"
      },
      "name": "Dr. R. Dhanalakshmi",
      "designation": "Associate Professor",
      "researchArea": "Computer Networks, Combinatorial Optimization Techniques, Data Analytics",
      "emailID": "dhanalakshmir@iiitt.ac.in",
      "src": "/faculty/Dhanalakshmi_cropped.jpg",
      "Incharge": "",
      "Institute": " Ph.D. (Jawaharlal Nehru Technological University Hyderabad)",
      "VidhwanLink": "https://vidwan.inflibnet.ac.in/profile/101692"
    },
    {
      "id": {
        "dept": "CSE",
        "deptID": "3"
      },
      "name": "Dr. N. Renugadevi",
      "designation": "Assistant Professor",
      "researchArea": "Information Security, Group Key Management, Secure Group Communication, Artificial Intelligence, Data Science, Remote Sensing & Geographic Information System(GIS), Digital Agriculture, Cognitive Radio Networks ",
      "emailID": "renugadevin@iiitt.ac.in",
      "src": "/faculty/Renuga.jpg",
      "Incharge": "Exam Cell, Alumni Association",
      "Institute": " Ph.D. CSE (NIT Tiruchirappalli)",
      "VidhwanLink": "https://vidwan.inflibnet.ac.in/profile/194473"
    },

    {
      "id": {
        "dept": "CSE",
        "deptID": "4"
      },
      "name": "Dr. Anoop Jacob Thomas",
      "designation": "Assistant Professor",
      "researchArea": "Medical Image Processing, Neuroimage Processing, Image Processing, Algorithms",
      "emailID": "anoopjt@iiitt.ac.in",
      "src": "/faculty/AnoopJacobThomas.jpg",
      "Incharge": "Campus Networking, EBSB, ERP, Exam Cell Member, Student Discipline, Hall Booking ",
      "Institute": "Ph.D. CSE (IIT Ropar)",
      "VidhwanLink": "https://vidwan.inflibnet.ac.in/profile/194478",
      "PersonalPage":"https://www.linkedin.com/in/anoopjt/"
    },
    {
      "id": {
        "dept": "CSE",
        "deptID": "5"
      },
      "name": "Dr. T. Sugirtha",
      "designation": "Assistant Professor",
      "researchArea": "  Computer vision, Deep Learning, Autonomous Driving, Augmented reality/Virtual Reality, Federated Learning, Full stack development.",
      "emailID": "sugirthat@iiitt.ac.in",
      "src": "/faculty/Sugirtha.jpg",
      "Incharge": "Girls Hostel Warden, Institute Mess",
      "Institute": "Ph.D. CSE (NIT Tiruchirappalli)",
      "VidhwanLink": ""
    },
    {
      "id": {
        "dept": "CSE",
        "deptID": "6"
      },
      "name": "Dr. M. Ambika",
      "designation": "Assistant Professor",
      "researchArea": "  AI, ML & DL, Recommendation System, Fuzzy Logic, Decision Support System, NLP, Precision Agriculture",
      "emailID": "ambikam@iiitt.ac.in",
      "src": "/faculty/AmbikaM.jpg",
      "Incharge": "Admission (UG & PG),Gem & CPP, Insurance, Purchase, 6th Convocation,Aikyam Magazine",
      "Institute": "Ph.D. (Anna University Chennai)",
      "VidhwanLink": "https://vidwan.inflibnet.ac.in/profile/588225",
      "PersonalPage": "https://iiitt.ac.in/downloads/Faculty_Profiles/Ambika_Resume.pdf"
    },
    {
      "id": {
        "dept": "CSE",
        "deptID": "7"
      },
      "name": "Dr. J. Kokila",
      "designation": "Assistant Professor",
      "researchArea": "Hardware Security, Information Security, Blockchain Technology, IoT Edge Computing, Computer Architecture",
      "emailID": "kokilaj@iiitt.ac.in",
      "src": "/faculty/KokilaJ.jpg",
      "Incharge": "Website development,maintenance and Social Media, clubs - (Website Dev, Media, Competitive Coding), E-Cell ",
      "Institute": "Ph.D. CSE (NIT Tiruchirappalli) under Visvesvaraya Phd Scheme",
      "VidhwanLink": "https://vidwan.inflibnet.ac.in/profile/212555",
      "PersonalPage":"https://sites.google.com/site/kokilajrsnitt/?pli=1"
    }
  ],
  "ECE": [
    {
      "id": {
        "dept": "ECE",
        "deptID": "1"
      },
      "name": "Dr. M. Senthil Sivakumar",
      "designation": "Assistant Professor , Head of the Department",
      "researchArea": " VLSI System Design and Testing, Analog and Mixed Signal IC Design, AI Hardware Accelerator and SoC Design",
      "emailID": "msenthilsivakumar@iiitt.ac.in",
      "src": "/faculty/MSenthilSivakumar.jpg",
      "Incharge": "NBA, NIRF, and Internship ",
      "Institute": "Ph.D. ECE (MIT Campus, Anna University Chennai)",
      "VidhwanLink": "https://iiitt.irins.org/profile/194474"
    },
    {
      "id": {
        "dept": "ECE",
        "deptID": "2"
      },
      "name": "Dr. G. Seetharaman",
      "designation": "Professor",
      "researchArea": "ASIC & FPGA Based Design",
      "emailID": "gsraman@iiitt.ac.in",
      "src": "/faculty/Seetharaman.jpg",
      "Incharge": "Registrar, Admission (UG & PG)-Chairman",
      "Institute": "Ph.D. CSE (NIT Tiruchirappalli) ",
      "VidhwanLink": "https://vidwan.inflibnet.ac.in/profile/194472",
      "PersonalPage":"https://iiitt.ac.in/downloads/Faculty_Profiles/Prof_GS_profile.pdf"
    },
    {
      "id": {
        "dept": "ECE",
        "deptID": "3"
      },
      "name": "Dr. R. Krishnamurthy",
      "designation": "Assistant Professor",
      "researchArea": " RF and Microwave Engineering, Optical Communication",
      "emailID": "krishnamurthyr@iiitt.ac.in",
      "src": "/faculty/Krishnamurthy.jpg",
      "Incharge": "Alhad and Atrang",
      "Institute": "Ph.D. ECE ( IISc. Bangalore) ",
      "VidhwanLink": "https://vidwan.inflibnet.ac.in/profile/562856",
      "PersonalPage":"https://sites.google.com/view/krishnamurthyramanujam/home?pli=1"
    },
    {
      "id": {
        "dept": "ECE",
        "deptID": "4"
      },
      "name": "Dr. Banoth Ravi",
      "designation": "Assistant Professor",
      "researchArea": " RF and Microwave Engineering, Optical Communication",
      "emailID": "ravib@iiitt.ac.in",
      "src": "/faculty/raviB_2024.jpeg",
      "Incharge": "Wireless Networks, Machine learning for Wireless communications, 5G/6G Intelligent Networks, Communication Networks, Vehicular Communications, Software Defined Networks.",
      "Institute": "Ph.D. ECE (IIT Dhanbad)",
      "VidhwanLink": "https://vidwan.inflibnet.ac.in/profile/562773",
      "PersonalPage":"https://sites.google.com/view/ravibanothiitism"
    },
    {
      "id": {
        "dept": "ECE",
        "deptID": "5"
      },
      "name": "Dr. D Suresh",
      "designation": "Assistant Professor",
      "researchArea": " VLSI; Phase change memory devices; Device simulations; Novel devices; Radiation–tolerant, non–volatile emerging memory devices",
      "emailID": "sureshd@iiitt.ac.in",
      "src": "/faculty/SureshD.jpg",
      "Incharge": "Sports & Gym (Out Door), NSS, Curricular and Extra-Curricular Activities",
      "Institute": "Ph.D. ECE (IIT Indore),   Post-doc. (IIT Madras)",
      "VidhwanLink": ""
    },
    {
      "id": {
        "dept": "ECE",
        "deptID": "6"
      },
      "name": "Dr. S. Padmathilagam",
      "designation": "Assistant Professor",
      "researchArea": "Antenna design and Measurements: Microstrip Antennas, Monopole Antennas, Reconfigurable Antennas, MIMO Antennas, WBAN Antennas; Microwave components and circuits.",
      "emailID": "sureshd@iiitt.ac.in",
      "src": "/faculty/PadmathilagamS.jpg",
      "Incharge": "Institute Library",
      "Institute": "Ph.D. ECE (CEG Campus, Anna University Chennai.)",
      "VidhwanLink": "https://vidwan.inflibnet.ac.in/profile/589595",
      "PersonalPage":"https://sites.google.com/iiitt.ac.in/padmathilagamprofile/home"
    },
    {
      "id": {
        "dept": "ECE",
        "deptID": "7"
      },
      "name": "Dr. M. Harish Adhithya",
      "designation": "Assistant Professor",
      "researchArea": " Antennas, Antenna Arrays, Metamaterials, Frequency Selective Surfaces, Shared Apertures, Microwave Components",
      "emailID": "harishadhithyam@iiitt.ac.in",
      "src": "/faculty/HarishAdhithyaM.JPG",
      "Incharge": "NIRF Member, Campus Maintenance, Clubs - IoT and Robotics, Computer Networking and Security, Fine Arts, C, Yoga, Literary and Debating, Photography",
      "Institute": "Ph.D. ECE (NIT Tiruchirappalli)",
      "VidhwanLink": "https://vidwan.inflibnet.ac.in/profile/588971"
    }
  ],
  "ME": [
    {
      "id": {
        "dept": "ME",
        "deptID": "1"
      },
      "name": "Dr. Velmurugan C",
      "designation": "Assistant Professor , Head of the Department",
      "researchArea": " Additive Manufacturing, Modelling and Simulation, Smart Materials, Shape Memory Alloys, Energy Storage Materials and Device, Battery- materials and performance.",
      "emailID": "velmuruganc@iiitt.ac.in",
      "src": "/faculty/VELMURUGANC.jpg",
      "Incharge": "BWC, BoG Member, Assistant Registrar Accounts, Outsourcing Agency",
      "Institute": "Ph.D. MEC. Eng. (NIT Tiruchirappalli)",
      "VidhwanLink": "https://vidwan.inflibnet.ac.in/profile/194479",
      "PersonalPage":"https://sites.google.com/view/velmuruganciiitt"
    }
  ],
  "Science & Humanities": [
    {
      "id": {
        "dept": "PHY",
        "deptID": "1"
      },
      "name": "Dr. Kamakshi K",
      "designation": "Assistant Professor , Head of the Department",
      "researchArea": "Photonics and Optoelectronic Devices",
      "emailID": "kamakshi@iiitt.ac.in",
      "src": "/faculty/Kamakshi1.jpeg",
      "Incharge": "Academic and Research",
      "Institute": "Ph.D. (IIT Roorkee) Post-doc. (University of Minho Portugal)",
      "VidhwanLink": "https://vidwan.inflibnet.ac.in/profile/194482"
    }
  ],
  "Mathematics": [
    {
      "id": {
        "dept": "MATH",
        "deptID": "1"
      },
      "name": "Dr. Jagadeeshwar Pashikanti",
      "designation": "Assistant Professor",
      "researchArea": "Computational Fluid Dynamics",
      "emailID": "jagadeeshwarp@iiitt.ac.in",
      "src": "/faculty/JagdishP.jpg",
      "Incharge": " Liaison Officer of OBC, ARC, ICC Member",
      "Institute": "Ph.D. (NIT Warangal )",
      "VidhwanLink": "https://iiitt.irins.org/profile/194477"
    }
  ],

  "English": [
    {
      "id": {
        "dept": "ENG",
        "deptID": "1"
      },
      "name": "Dr. V. Sindhu",
      "designation": "Assistant Professor",
      "researchArea": "Applied Linguistics, English Language Teaching",
      "emailID": "sindhuv@iiitt.ac.in",
      "src": "/faculty/Sindhu.jpg",
      "Incharge": "Assistant Registrar, Aikyam - Multi-lingual Student Magazine, Annual Report – Preparation & Printing, Ministry Reply",
      "Institute": "Ph.D. (CEG Campus, Anna University Chennai.)",
      "VidhwanLink": "https://vidwan.inflibnet.ac.in/profile/194483",
      "PersonalPage":"https://iiitt.ac.in/downloads/Faculty_Profiles/Sindhu_Profile.pdf"
    }
  ]
}