{
  "data": [
    {
      "title": " 2025-26 SESSION ODD SEMESTER ",
      "data": [
        {
          "title": "Academic calendar_ODD_M.Tech.pdf",
          "link": "calendar/Academic calendar_ODD_M.Tech.pdf"
        },
        {
          "title": "Academic calendar_ODD_BTECH_PHD_2025.pdf ",
          "link": "calendar/Academic calendar_ODD_BTECH_PHD_2025.pdf"
        },
        {
          "title": "B.TECH ACADEMIC CALENDAR - ODD SEMESTER 2025",
          "link": "notices/Academic calendar_ODD-Annex XII_BTech_2025.pdf"
        }
      ]
    },
    {
      "title": " 2024-25 SESSION EVEN SEMESTER ",
      "data": [
        {
          "title": "Academic Calendar - B.Tech.(II,IV,VI,VIII semester), M.Tech.(II, IV semester), & M.Sc.(II semester)",
          "link": "notices/Academic calendar_EVEN 2024-2025.pdf"
        },
        {
          "title": "Academic calendar - PhD_2025-26 (Even Semester)",
          "link": "notices/Academic calendar__EVEN_PhD_25-26.pdf"
        }
      ]
    },


    {
      "title": " 2024-25 SESSION ODD SEMESTER",
      "data": [
        {
          "title": "Academic Calendar - REDO COURSE 2024-25",
          "link": "notices/Academic%20calendar_Redo_2024.pdf"
        },
        {
          "title": "Academic Calendar - B.Tech. (III,IV,VII semester)",
          "link": "/calendar/Academic_calendar_2024_25_BTech_II_III_IV.pdf"
        },
        {
          "title": "Academic Calendar - M.Tech.(II semester)",
          "link": "/calendar/Academic_calendar_2024_25_MTech_II.pdf"
        },
        {
          "title": "Academic Calendar - B.Tech.(I yr), M.Tech.(I yr), M.Sc.(I yr)",
          "link": "/calendar/Academic_calendar_2024_25_I%20year.pdf"
        }
      ]
      
    },
    {
      "title": " (EVEN SEMESTER / 2023-24 SESSION)",
      "data": [
        {
          "title": "Revised Academic Calendar - B.Tech. (II,IV,VI,VIII semester) & M.Tech.(II semester)",
          "link": "/calendar/Academic_Calender_2023_24_EVEN_Revised.pdf"
        },
        {
          "title": "Academic Calendar - B.Tech. (II,IV,VI,VIII semester) & M.Tech.(II semester)",
          "link": "/calendar/Academic_Calender_2023_24_EVEN.pdf"
        }
      ]
    },
    {
      "title": " (ODD SEMESTER / 2023-24 SESSION)",
      "data": [
        {
          "title": "Academic Calendar - B.Tech.(I semester), M.Tech.(I semester) and M.Sc.(I semester)",
          "link": "/calendar/Academic_Calendar_ODD_I_BTECH_MTECH_MSC.pdf"
        },
        {
          "title": "Academic Calendar ( B.Tech. ( III, V, VII semesters)",
          "link": "/calendar/Academic_Calendar_2023_24.pdf"
        },
        {
          "title": "Academic Calendar ( Redo Course )",
          "link": "/calendar/Academic_Calendar_Redo_May2023.pdf"
        }
      ]
    },
    {
      "title": " (EVEN SEMESTER / 2022-23 SESSION)",
      "data": [
        {
          "title": "Academic Calendar ( B.Tech. (II Semester) ) - March 2023 Session )",
          "link": "/calendar/BTech_II_Sem_Academic_Calendar_AY2022_23.pdf"
        },
        {
          "title": "Academic Calendar ( B.Tech. ( IV, VI, VIII semesters) and M.Tech. ( II & IV semesters ) - January 2023 Session )",
          "link": "/calendar/AcademicCalender_2022_23_EVEN.pdf"
        }
      ]
    },
    {
      "title": " (ODD SEMESTER / 2022-23 SESSION)",
      "data": [
        {
          "title": "Academic Calendar ( B.Tech. (I Semester) ) - November 2022 Session )",
          "link": "/calendar/BTech_I_Sem_Academic_Calendar_AY2022_23.pdf"
        },
        {
          "title": "Academic Calendar ( B.Tech. ( III, V, VII semesters) and M.Tech. ( I & III semesters ) - September 2022 Session )",
          "link": "Academic Calendar ( B.Tech. (I Semester) ) - November 2022 Session )"
        }
      ]
    },
    {
      "title": " (EVEN SEMESTER / 2021-22 SESSION)",
      "data": [
        {
          "title": "Academic Calendar ( B.Tech. ( IV, VI, VIII ) and M.Tech. ( II ) - January 2022 Session )",
          "link": "/calendar/EVEN_Semester_2021-22_BTech(IV_IV_VIII)_and_MTech(II%20Sem)_Revised.pdf"
        },
        {
          "title": "Academic Calendar ( B.Tech. ( II ) - April 2022 Session )",
          "link": "/calendar/AcademicCalendar_2021-22EVEN_SEM2.pdf"
        }
      ]
    },
    {
      "title": " (ODD SEMESTER / 2021-22 SESSION)",
      "data": [
        {
          "title": "1. Academic Calendar ( B.Tech. (V, VII ) - July 2021 Session )",
          "link": "ODDSemester2021-22.pdf"
        },
        {
          "title": "2. Academic Calendar ( B.Tech. ( III ) - August 2021 Session )",
          "link": "ODD_Semester_2021-22_II_year.pdf"
        }
      ]
    },
    {
      "title": " (EVEN SEMESTER / 2020-21 SESSION)",
      "data": [
        {
          "title": "1. Academic Calendar ( B.Tech. ( IV, VI, VIII ) - Jan 2021 Session )",
          "link": "Academic_CalendarEVEN_Semester_2020-2021.pdf"
        },
        {
          "title": "2. Academic Calendar ( B.Tech. ( II ) - April 2021 Session )",
          "link": "EVEN_Semester_2020-21_FY.pdf"
        }
      ]
    },
    {
      "title": " (ODD SEMESTER / 2020-21 SESSION)",
      "data": [
        {
          "title": "1. Academic Calendar ( B.Tech. ( III, V, VII ) - August 2020 Session )",
          "link": "Academic_CalendarODD_Semester_2020-2021.pdf"
        },
        {
          "title": "2. Academic Calendar ( B.Tech. ( I ) - December 2020 Session )",
          "link": "FirstSemester_ODD_Semester_2020-21.pdf"
        }
      ]
    },
    {
      "title": " (EVEN SEMESTER / January 2020 SESSION)",
      "data": [
        {
          "title": "Academic Calendar ( January 2020 Session )",
          "link": "Even_Semester_2019-20-Academic_calendar.pdf"
        }
      ]
    },
    {
      "title": " (EVEN SEMESTER / JANUARY 2019 SESSION)",
      "data": [
        {
          "title": "Academic Calendar ( January 2019 Session )",
          "link": "AcademicCalendar-Jan2019.pdf"
        }
      ]
    },
    {
      "title": "TIME TABLE (EVEN SEMESTER / JANUARY 2019 SESSION)",
      "data": [
        {
          "title": "Time Table ( January 2019 Session )",
          "link": "ExamSchedule-Jan2019.pdf"
        }
      ]
    },
    {
      "title": " (ODD SEMESTER / JULY 2018 SESSION)",
      "data": [
        {
          "title": "Academic Calendar ( B.Tech. ( III, V, VII ) - July Session )",
          "link": "Calendar_2018_Odd1.pdf"
        },
        {
          "title": "Academic Calendar ( B.Tech. ( I ) - July Session )",
          "link": "I-Calendar_2018_Odd.pdf"
        }
      ]
    },
    {
      "title": "TIME TABLE (ODD SEMESTER / JULY 2018 SESSION)",
      "data": [
        {
          "title": "Time Table ( B.Tech. ( III, V, VII ) - July Session )",
          "link": "CSE_ODDsem_Timetable(18-19).pdf"
        },
        {
          "title": "Time Table ( B.Tech. ( I ) - July Session )",
          "link": "ECE_ODDsem_Timetable(18-19).pdf"
        }
      ]
    }
  ]
}





